<annotation>
	<folder>RED</folder>
	<filename>IMG_15443326897.jpg</filename>
	<path>/jixj/term3/p055/training/RealCarTrack_Classified_Imgs/RED/IMG_15443326897.jpg</path>
	<source>
		<database>Unknown</database>
	</source>
	<size>
		<width>1368</width>
		<height>1096</height>
		<depth>3</depth>
	</size>
	<segmented>0</segmented>
	<object>
		<name>red</name>
		<pose>Unspecified</pose>
		<truncated>0</truncated>
		<difficult>0</difficult>
		<bndbox>
			<xmin>224</xmin>
			<ymin>345</ymin>
			<xmax>295</xmax>
			<ymax>538</ymax>
		</bndbox>
	</object>
</annotation>
