<annotation>
	<folder>RED</folder>
	<filename>IMG_154372281207.jpg</filename>
	<path>/jixj/term3/p015/SimulatorTrack1_Classified_Imgs/RED/IMG_154372281207.jpg</path>
	<source>
		<database>Unknown</database>
	</source>
	<size>
		<width>800</width>
		<height>600</height>
		<depth>3</depth>
	</size>
	<segmented>0</segmented>
	<object>
		<name>red</name>
		<pose>Unspecified</pose>
		<truncated>0</truncated>
		<difficult>0</difficult>
		<bndbox>
			<xmin>188</xmin>
			<ymin>276</ymin>
			<xmax>240</xmax>
			<ymax>395</ymax>
		</bndbox>
	</object>
	<object>
		<name>red</name>
		<pose>Unspecified</pose>
		<truncated>0</truncated>
		<difficult>0</difficult>
		<bndbox>
			<xmin>416</xmin>
			<ymin>279</ymin>
			<xmax>467</xmax>
			<ymax>396</ymax>
		</bndbox>
	</object>
	<object>
		<name>red</name>
		<pose>Unspecified</pose>
		<truncated>0</truncated>
		<difficult>0</difficult>
		<bndbox>
			<xmin>647</xmin>
			<ymin>286</ymin>
			<xmax>702</xmax>
			<ymax>400</ymax>
		</bndbox>
	</object>
</annotation>
